{
  "authors": [
    {
      "authorId": "2939438", 
      "name": "Yi Luan", 
      "url": "https://www.semanticscholar.org/author/2939438"
    }, 
    {
      "authorId": "2567583", 
      "name": "Yangfeng Ji", 
      "url": "https://www.semanticscholar.org/author/2567583"
    }, 
    {
      "authorId": "2548384", 
      "name": "Hannaneh Hajishirzi", 
      "url": "https://www.semanticscholar.org/author/2548384"
    }, 
    {
      "authorId": "2089181", 
      "name": "Boyang Li", 
      "url": "https://www.semanticscholar.org/author/2089181"
    }
  ], 
  "citationVelocity": 0, 
  "citations": [
    {
      "isInfluential": false, 
      "paperId": "0698c53f1be70384ca948f958f997d7a54617487", 
      "title": "Predicting the Quality of Short Narratives from Social Media", 
      "url": "https://www.semanticscholar.org/paper/0698c53f1be70384ca948f958f997d7a54617487", 
      "venue": "IJCAI", 
      "year": 2017
    }, 
    {
      "isInfluential": false, 
      "paperId": "ae88624ef068a19ef2593103ecfa6b5837c4ff04", 
      "title": "Learning Distributed Representations of Texts and Entities from Knowledge Base", 
      "url": "https://www.semanticscholar.org/paper/ae88624ef068a19ef2593103ecfa6b5837c4ff04", 
      "venue": "ArXiv", 
      "year": 2017
    }
  ], 
  "doi": null, 
  "influentialCitationCount": 0, 
  "paperId": "81af4e14050c410e2afee226be583088a9791ddf", 
  "references": [
    {
      "isInfluential": true, 
      "paperId": "1ada7e038d9dd3030cdbc7b0fc1eb041c1e4fb6b", 
      "title": "Unsupervised Induction of Semantic Roles within a Reconstruction-Error Minimization Framework", 
      "url": "https://www.semanticscholar.org/paper/1ada7e038d9dd3030cdbc7b0fc1eb041c1e4fb6b", 
      "venue": "HLT-NAACL", 
      "year": 2015
    }, 
    {
      "isInfluential": false, 
      "paperId": "41ac86c2639ff1e6c90767ddbcdd8566ae24da10", 
      "title": "Calibrating Features for Semantic Role Labeling", 
      "url": "https://www.semanticscholar.org/paper/41ac86c2639ff1e6c90767ddbcdd8566ae24da10", 
      "venue": "EMNLP", 
      "year": 2004
    }, 
    {
      "isInfluential": false, 
      "paperId": "4546c7b4d2103523b104daddea6c7eaa1925cf12", 
      "title": "MaltParser: A Language-Independent System for Data-Driven Dependency Parsing", 
      "url": "https://www.semanticscholar.org/paper/4546c7b4d2103523b104daddea6c7eaa1925cf12", 
      "venue": "Natural Language Engineering", 
      "year": 2005
    }, 
    {
      "isInfluential": false, 
      "paperId": "04a8d271bc4384dbfbb417bfb625feb01cb44666", 
      "title": "Automatic Labeling of Semantic Roles", 
      "url": "https://www.semanticscholar.org/paper/04a8d271bc4384dbfbb417bfb625feb01cb44666", 
      "venue": "Computational Linguistics", 
      "year": 2000
    }, 
    {
      "isInfluential": false, 
      "paperId": "14c146d457bbd201f3a117ee9c848300d341e5d0", 
      "title": "The CoNLL 2008 Shared Task on Joint Parsing of Syntactic and Semantic Dependencies", 
      "url": "https://www.semanticscholar.org/paper/14c146d457bbd201f3a117ee9c848300d341e5d0", 
      "venue": "CoNLL", 
      "year": 2008
    }, 
    {
      "isInfluential": true, 
      "paperId": "0183b3e9d84c15c7048e6c2149ed86257ccdc6cb", 
      "title": "Dependency-Based Word Embeddings", 
      "url": "https://www.semanticscholar.org/paper/0183b3e9d84c15c7048e6c2149ed86257ccdc6cb", 
      "venue": "ACL", 
      "year": 2014
    }, 
    {
      "isInfluential": false, 
      "paperId": "73183e53ce4843471d655a3bb6eee0384ca86c70", 
      "title": "Multilingual Semantic Role Labeling", 
      "url": "https://www.semanticscholar.org/paper/73183e53ce4843471d655a3bb6eee0384ca86c70", 
      "venue": "CoNLL Shared Task", 
      "year": 2009
    }, 
    {
      "isInfluential": false, 
      "paperId": "41d3880c21286f66062da24282b6760cb4fe3f30", 
      "title": "Semi-Supervised Semantic Role Labeling via Structural Alignment", 
      "url": "https://www.semanticscholar.org/paper/41d3880c21286f66062da24282b6760cb4fe3f30", 
      "venue": "Computational Linguistics", 
      "year": 2012
    }, 
    {
      "isInfluential": false, 
      "paperId": "ed73c8b844f9bc19170fd904c30c402fe215b9b1", 
      "title": "Unsupervised Semantic Role Induction via Split-Merge Clustering", 
      "url": "https://www.semanticscholar.org/paper/ed73c8b844f9bc19170fd904c30c402fe215b9b1", 
      "venue": "ACL", 
      "year": 2011
    }, 
    {
      "isInfluential": false, 
      "paperId": "85701003162f5907f24a614ff6b21cfb731560c7", 
      "title": "The Importance of Syntactic Parsing and Inference in Semantic Role Labeling", 
      "url": "https://www.semanticscholar.org/paper/85701003162f5907f24a614ff6b21cfb731560c7", 
      "venue": "Computational Linguistics", 
      "year": 2008
    }, 
    {
      "isInfluential": false, 
      "paperId": "0d97cbb7a79db7cee196df18e76e6916060917c1", 
      "title": "Semantic Role Chunking Combining Complementary Syntactic Views", 
      "url": "https://www.semanticscholar.org/paper/0d97cbb7a79db7cee196df18e76e6916060917c1", 
      "venue": "CoNLL", 
      "year": 2005
    }, 
    {
      "isInfluential": false, 
      "paperId": "2a774eaba7581288221edbbfab267d1866ccab99", 
      "title": "Semantic Frame Identification with Distributed Word Representations", 
      "url": "https://www.semanticscholar.org/paper/2a774eaba7581288221edbbfab267d1866ccab99", 
      "venue": "ACL", 
      "year": 2014
    }, 
    {
      "isInfluential": true, 
      "paperId": "762b63d2eb86f8fd0de98a08561b77527ae8f165", 
      "title": "Distributed Representations of Words and Phrases and their Compositionality", 
      "url": "https://www.semanticscholar.org/paper/762b63d2eb86f8fd0de98a08561b77527ae8f165", 
      "venue": "NIPS", 
      "year": 2013
    }, 
    {
      "isInfluential": false, 
      "paperId": "05aba481e8a221df5d8775a3bb749001e7f2525e", 
      "title": "Adaptive Subgradient Methods for Online Learning and Stochastic Optimization", 
      "url": "https://www.semanticscholar.org/paper/05aba481e8a221df5d8775a3bb749001e7f2525e", 
      "venue": "COLT", 
      "year": 2010
    }, 
    {
      "isInfluential": false, 
      "paperId": "c34e41312b47f60986458759d5cc546c2b53f748", 
      "title": "End-to-end learning of semantic role labeling using recurrent neural networks", 
      "url": "https://www.semanticscholar.org/paper/c34e41312b47f60986458759d5cc546c2b53f748", 
      "venue": "ACL", 
      "year": 2015
    }, 
    {
      "isInfluential": false, 
      "paperId": "2538e3eb24d26f31482c479d95d2e26c0e79b990", 
      "title": "Natural Language Processing (almost) from Scratch", 
      "url": "https://www.semanticscholar.org/paper/2538e3eb24d26f31482c479d95d2e26c0e79b990", 
      "venue": "Journal of Machine Learning Research", 
      "year": 2011
    }, 
    {
      "isInfluential": false, 
      "paperId": "00383c9389ac9eb42029e3a84e7262cf47561de2", 
      "title": "Frame-Semantic Role Labeling with Heterogeneous Annotations", 
      "url": "https://www.semanticscholar.org/paper/00383c9389ac9eb42029e3a84e7262cf47561de2", 
      "venue": "ACL", 
      "year": 2015
    }, 
    {
      "isInfluential": false, 
      "paperId": "053620fe801399d0359749d8d1c807993ee5cef9", 
      "title": "A Bayesian Approach to Unsupervised Semantic Role Induction", 
      "url": "https://www.semanticscholar.org/paper/053620fe801399d0359749d8d1c807993ee5cef9", 
      "venue": "EACL", 
      "year": 2012
    }, 
    {
      "isInfluential": false, 
      "paperId": "980c2517368aaa0d4a4972ff7bcc5cf3ec41656a", 
      "title": "SimLex-999: Evaluating Semantic Models With (Genuine) Similarity Estimation", 
      "url": "https://www.semanticscholar.org/paper/980c2517368aaa0d4a4972ff7bcc5cf3ec41656a", 
      "venue": "Computational Linguistics", 
      "year": 2015
    }, 
    {
      "isInfluential": false, 
      "paperId": "a253f215833a0533bf2749964ba95577f122e33c", 
      "title": "Unsupervised Semantic Role Induction with Global Role Ordering", 
      "url": "https://www.semanticscholar.org/paper/a253f215833a0533bf2749964ba95577f122e33c", 
      "venue": "ACL", 
      "year": 2012
    }, 
    {
      "isInfluential": false, 
      "paperId": "5f8bc4807fec3ad946d10b187c0f1ea72701ca2c", 
      "title": "Evaluating FrameNet-style semantic parsing: the role of coverage gaps in FrameNet", 
      "url": "https://www.semanticscholar.org/paper/5f8bc4807fec3ad946d10b187c0f1ea72701ca2c", 
      "venue": "COLING", 
      "year": 2010
    }, 
    {
      "isInfluential": false, 
      "paperId": "084f6b2bc0d1f63fa1364ec23ec2ac0d4de0538b", 
      "title": "Towards Robust Semantic Role Labeling", 
      "url": "https://www.semanticscholar.org/paper/084f6b2bc0d1f63fa1364ec23ec2ac0d4de0538b", 
      "venue": "Computational Linguistics", 
      "year": 2007
    }, 
    {
      "isInfluential": false, 
      "paperId": "0825788b9b5a18e3dfea5b0af123b5e939a4f564", 
      "title": "Glove: Global Vectors for Word Representation", 
      "url": "https://www.semanticscholar.org/paper/0825788b9b5a18e3dfea5b0af123b5e939a4f564", 
      "venue": "EMNLP", 
      "year": 2014
    }, 
    {
      "isInfluential": true, 
      "paperId": "cb75d65998b34e29124fee8578a2d667f05264d4", 
      "title": "Similarity-Driven Semantic Role Induction via Graph Partitioning", 
      "url": "https://www.semanticscholar.org/paper/cb75d65998b34e29124fee8578a2d667f05264d4", 
      "venue": "Computational Linguistics", 
      "year": 2014
    }, 
    {
      "isInfluential": false, 
      "paperId": "452a9d49f9a5a99c0dab0e31ec30ffe1cfd20e2e", 
      "title": "Probabilistic Frame-Semantic Parsing", 
      "url": "https://www.semanticscholar.org/paper/452a9d49f9a5a99c0dab0e31ec30ffe1cfd20e2e", 
      "venue": "HLT-NAACL", 
      "year": 2010
    }, 
    {
      "isInfluential": false, 
      "paperId": "48cc672ad0f18b919e0c95ccbed340a0d71bddbd", 
      "title": "Semantic Role Labeling with Neural Network Factors", 
      "url": "https://www.semanticscholar.org/paper/48cc672ad0f18b919e0c95ccbed340a0d71bddbd", 
      "venue": "EMNLP", 
      "year": 2015
    }, 
    {
      "isInfluential": false, 
      "paperId": "308ba6a27e6a5252bab8d043f5251ab4469458b5", 
      "title": "From TreeBank to PropBank", 
      "url": "https://www.semanticscholar.org/paper/308ba6a27e6a5252bab8d043f5251ab4469458b5", 
      "venue": "LREC", 
      "year": 2002
    }, 
    {
      "isInfluential": true, 
      "paperId": "4b713bc1fa91cf5659334a526a9c580fb26e4acb", 
      "title": "Distributed Representations for Unsupervised Semantic Role Labeling", 
      "url": "https://www.semanticscholar.org/paper/4b713bc1fa91cf5659334a526a9c580fb26e4acb", 
      "venue": "EMNLP", 
      "year": 2015
    }
  ], 
  "title": "Multiplicative Representations for Unsupervised Semantic Role Induction", 
  "url": "https://www.semanticscholar.org/paper/81af4e14050c410e2afee226be583088a9791ddf", 
  "venue": "ACL", 
  "year": 2016
}
